yahoo_display_test/__init__.py
yahoo_display_test/api_client.py
yahoo_display_test/configuration.py
yahoo_display_test/exceptions.py
yahoo_display_test/rest.py
yahoo_display_test/api/__init__.py
yahoo_display_test/api/ab_test_service_api.py
yahoo_display_test/api/account_authority_service_api.py
yahoo_display_test/api/account_link_service_api.py
yahoo_display_test/api/account_management_service_api.py
yahoo_display_test/api/account_service_api.py
yahoo_display_test/api/account_tracking_url_service_api.py
yahoo_display_test/api/ad_group_ad_label_service_api.py
yahoo_display_test/api/ad_group_ad_service_api.py
yahoo_display_test/api/ad_group_label_service_api.py
yahoo_display_test/api/ad_group_service_api.py
yahoo_display_test/api/ad_group_target_service_api.py
yahoo_display_test/api/app_link_service_api.py
yahoo_display_test/api/audience_list_service_api.py
yahoo_display_test/api/audit_log_service_api.py
yahoo_display_test/api/balance_service_api.py
yahoo_display_test/api/base_account_service_api.py
yahoo_display_test/api/brand_lift_service_api.py
yahoo_display_test/api/budget_order_service_api.py
yahoo_display_test/api/campaign_label_service_api.py
yahoo_display_test/api/campaign_service_api.py
yahoo_display_test/api/contents_keyword_idea_service_api.py
yahoo_display_test/api/contents_keyword_list_service_api.py
yahoo_display_test/api/conversion_group_service_api.py
yahoo_display_test/api/conversion_tracker_service_api.py
yahoo_display_test/api/dictionary_service_api.py
yahoo_display_test/api/feed_data_service_api.py
yahoo_display_test/api/feed_ftp_request_service_api.py
yahoo_display_test/api/feed_ftp_service_api.py
yahoo_display_test/api/feed_item_service_api.py
yahoo_display_test/api/feed_service_api.py
yahoo_display_test/api/feed_set_service_api.py
yahoo_display_test/api/guaranteed_ad_group_ad_service_api.py
yahoo_display_test/api/guaranteed_ad_group_service_api.py
yahoo_display_test/api/guaranteed_campaign_service_api.py
yahoo_display_test-1.0.0.dist-info/METADATA
yahoo_display_test-1.0.0.dist-info/WHEEL
yahoo_display_test-1.0.0.dist-info/top_level.txt
yahoo_display_test-1.0.0.dist-info/RECORD
